triqs_hubbardI/__init__.py
triqs_hubbardI/solver.py
triqs_hubbardI/version.py
triqs_hubbardI-3.3.0.dist-info/COPYING.txt
triqs_hubbardI-3.3.0.dist-info/LICENSE.txt
triqs_hubbardI-3.3.0.dist-info/METADATA
triqs_hubbardI-3.3.0.dist-info/WHEEL
triqs_hubbardI-3.3.0.dist-info/top_level.txt
triqs_hubbardI-3.3.0.dist-info/RECORD
