Metadata-Version: 2.1
Name: triqs_hubbardI
Version: 3.3.0
Summary: Hubbard-I impurity solver based on the TRIQS library (triqs.github.io)
Author-email: TRIQS <triqs@flatironinstitute.org>
Project-URL: Homepage, https://triqs.github.io/hubbardI
Project-URL: Bug Tracker, https://github.com/triqs/hubbardI/issues
Keywords: triqs,hubbard-I,impurity solver,dmft
Classifier: Programming Language :: Python :: 3
Classifier: License :: OSI Approved :: GNU General Public License v3 (GPLv3)
Classifier: Operating System :: OS Independent
Requires-Python: >=3.7
License-File: LICENSE.txt
License-File: COPYING.txt
Requires-Dist: numpy
Requires-Dist: scipy
